cryptwood/AES256cryptor.py
cryptwood/CWconfig.py
cryptwood/__init__.py
cryptwood/cryptwood.py
cryptwood-0.1.7.dist-info/LICENSE
cryptwood-0.1.7.dist-info/METADATA
cryptwood-0.1.7.dist-info/WHEEL
cryptwood-0.1.7.dist-info/top_level.txt
cryptwood-0.1.7.dist-info/RECORD
