Metadata-Version: 2.1
Name: cryptwood
Version: 0.1.7
Summary: A tool for encrypting sensitive data
Home-page: https://github.com/RedForestLonvor/cryptwood
Author: RedForestLonvor
Author-email: redforestlonvor@outlook.com
License: GPL-3.0
Classifier: Development Status :: 2 - Pre-Alpha
Classifier: Intended Audience :: Developers
Classifier: Programming Language :: Python :: 3
Classifier: Operating System :: OS Independent
License-File: LICENSE
Requires-Dist: cryptography (>=3.0)
